Workbook

Sheet gen-abstract
A2: NAME OF WORK :- CONSTRUCTION OF COMMERCIAL COMPLEX FOR PANCHAYAT SAMITI GIRWA, UDAIPUR
A5: GENERAL ABSTRACT OF COST
B7: PART 'A' CIVIL WORK BASEMENT, GROUND FLOOR AND FIRST FLOOR | F7: Rs. | G7: =GF1_ABS!G263 -> #REF!
B9: PART 'B' SANITARY & WATER SUPPLY WORK | F9: Rs. | G9: ='sanitary-abs'!G47 -> 81418
B11: PART 'C' ELECTRIC WORK @ 12% OF Civil Work | F11: Rs. | G11: =G7*0.12 -> #REF!
F13: TOTAL Rs. | G13: =SUM(G7:G11) -> #REF!
B15: Add @ 5 % for Electric Fixtures On Civil Work Part 'A'
C16: i.e. on Rs. | D16: =G7 -> #REF! | F16: Rs. | G16: =ROUNDUP(D16*0.05,0) -> #REF!
E17: GRAND TOTAL Rs. | G17: =SUM(G13:G16) -> #REF!
F19: SAY Rs. | G19: =ROUNDUP(G17/1000000,2)*10 -> #REF!
G20: Lacs.
E22: CHARTERED ENGINEER,
E23: TEJHANS INVESTMENTS, UDAIPUR

Sheet GF1_ABS
A1: ='gen-abstract'!A2 -> NAME OF WORK :- CONSTRUCTION OF COMMERCIAL COMPLEX FOR PANCHAYAT SAMITI GIRWA, UDAIPUR
A2: PART 'A' CIVIL WORK BASEMENT, GROUND FLOOR AND FIRST FLOOR
A3: ABSTRACT OF COST
A4: S.No. | B4: Particulars. | C4: Quantity | E4: Rate | F4: Unit | G4: Amount
A5: 1 | B5: Earth work in excavation in foundation trenches or drains including dressing of sides and ramming of bottoms, lift up to 1.5 Mtr. including taking out the excavated soil and depositing and refilling of jhiri with watering & ramming and disposal of surplus excavated soil as directed within a lead of 50 meter. All kinds of soil. | C5: =GF1_MES!K51 -> 1548.5904 | D5: Cum | E5: 92 | F5: P Cum | G5: =C5*E5 -> 142470.32
A6: 2 | B6: Filling available excavated earth (excluding rock) in trenches, plinth side of foundation etc. in layers not exceeding 20 cm. in depth , consolidating each deposited layer by ramming and watering including lead upto 50Mtr. and lift upto 1.5Mtr. | C6: =GF1_MES!K80 -> 1168.582 | D6: Cum | E6: 44 | F6: P Cum | G6: =C6*E6 -> 51417.608
A7: 3 | B7: Providing and injection Chloropyrifous Emulsifiable concentrate 20 % with 1 % concentration for PRE-CONSGTRUCTIONAL Anti termite treatment as per IS 6313 part III and amended from time to time and creating a continous chemical barrier under and around the column pits, wall trenches, basement excavation, top surface of plinth filling, junction of wall and floor along the external perimeter of building expansion joints, over the top surface of consolidated earth of which aproch is to be laid surrounding of pipes and conduits etc. complete as per specification (Plinth floor area only shall be measured for payment.) | C7: =GF1_MES!K84 -> 1290.492 | D7: Sqm | E7: 180 | G7: =C7*E7 -> 232288.56
A8: 4 | B8: Providing and laying in position cement concrete including curing compaction etc. of specified grade excluding the cost of centering and shuttering =All up to plinth leve 1:4:8 (1Cement :4 Coarse Sand :8 Graded stone aggregate 40 mm nominal size | C8: =GF1_MES!K107 -> 211.8603 | D8: Cum | E8: 2346 | F8: P Cum | G8: =C8*E8 -> 497024.26
A9: 5 | B9: Providing and laying in position specified grade of reinforcement cement concrete all RCC structural elements upto plinth level including curing compaction finishing with rendering in cement sand mortar 1:3 ( 1 cement : 3 coarse sand) and making good the joints excluding the cost of centering shuttering and reinforcementlevel. M25 grade Design mix | C9: =GF1_MES!K219 -> 467.7162 | D9: Cum | E9: 4912 | F9: P Cum | G9: =C9*E9 -> 2297422
A10: 6 | B10: Providing and layin in position specified grade of cement concrete for RCC Structure elements unto floor three level including curing, compaction, finishing with rendering in cement sand mortar 1:3 (1 cement ; 3 coarse sand) and making good the joints excluding the cost of centering shuttering and reinforcement forshuttering and reinforcement : M25 grade Design mix | C10: =GF1_MES!K230 -> 188.1031 | D10: Cum | E10: 5240 | F10: P Cum | G10: =C10*E10 -> 985660.27
A11: 7 | B11: Providing and layin in position specified grade of cement concrete for RCC Structure elements unto floor three level including curing, compaction, finishing with rendering in cement sand mortar 1:3 (1 cement ; 3 coarse sand) and making good the joints excluding the cost of centering shuttering and reinforcement forshuttering and reinforcement : Walls (any thickness) including attached pilasters, buttresses, plinth and string courses, fillets, columns, pillars, piers, abutments, posts and struts etc. M20 grade Nominal Mix | C11: 97 | D11: cum | E11: 4319 | F11: P Cum | G11: =C11*E11 -> 418943
A12: 9 | B12: beams suspended floors roofs griders having slopes up to 15 digree C, landings balconies shelves chajjas lintels bands plain window sills staircases and spiral staircases M20 grade nominal mix | C12: 1993 | D12: Cum | E12: 4300 | F12: P Cum | G12: =C12*E12 -> 8569900
A13: 8 | B13: Centering and shuttering with plywood or steel sheets including strutting, propping, bracing both ways and removal of formwork for foundations in basements rafts, footings, strap beams, bases of columns , etc. up to plinth level. | C13: 3598 | D13: Sqm | E13: 85 | G13: =C13*E13 -> 305830
A14: 9 | B14: Centering & shuttering with ply wood or steel sheets including shuttering , propping, barcing both waves with widen members and removal of form work up to floor three level for:
B15: (A) Suspended floors, roofs, landings, staircases, balconies, girders, cantilevers, bands , coping, bed plates, anchor blocks, sills, chhajjas lintel, beam etc. | C15: 13607 | D15: Sqm | E15: 164 | G15: =C15*E15 -> 2231548
B16: (B) Columns, pillars, posts and struts etc. | C16: 2574 | D16: Sqm | E16: 156 | G16: =C16*E16 -> 401544
A17: 12 | B17: Providing and fabricating reinforcement for R.C.C. work including straightening, cutting, bending, placing in position and binding (including cost of binding wire) all complete up to floor three level. Tremo Mechanically treated bars | C17: =GF1_MES!K247 -> 84030.26 | D17: Kg | E17: 56 | G17: =C17*E17 -> 4705694.5
A18: 13 | B18: Provinding hoisting and fixing up to floor three level precast reinforced concrte work in nominal M20 grade mix including cost of required centering, shuttering finishing smooth with 6 mm thick cement plastr 1:3 ( 1 cement : 3 fine sand) on exposed surface complete excluding cost of reinforcement.Lintels, beams and bressumers including setting in cement mortar 1:3 (1 cement : 3 course sand) aggregate 20mm nominal size. | C18: 5 | D18: cum | E18: 3618 | F18: P Cum | G18: =C18*E18 -> 18090
A19: 14 | B19: Providing and fixing precast R.C.C. slab in M15 nominal mix per design unto 30mm thick for shelves etc, including cost of reinforcement consisting of wire of mesh 100x100mmx4mm with fine finish. | C19: 35 | D19: Sqm | E19: 284 | G19: =C19*E19 -> 9940
A20: 15 | B20: Brick masonry in foundation and plinth with bricks of class designation 75 in : Cement mortar 1 : 6 (1 cement : 6 coarse sand) | C20: 1105 | D20: Cum | E20: 2530 | F20: P Cum | G20: =C20*E20 -> 2795650
A21: 16 | B21: Add extra over item No.5.1 for brick work in super structure upto third storey. | C21: 1105 | D21: Cum | E21: 140 | F21: P Cum | G21: =C21*E21 -> 154700
A22: 17 | B22: Half brick masonry in foundation & plinth using bricks of designation 75 in Cement mortar 1 : 4 (1 cement : 4 coarse sand) | C22: 4067 | D22: Sqm | E22: 293 | G22: =C22*E22 -> 1191631
A23: 18 | B23: Add extra over item no 5.8 for half brick masonry in superstructure up to third storey.including cost of hoop reinforcement (2 nos 6 mm dia MS bars at every fourth course | C23: 4067 | D23: Sqm | E23: 48 | G23: =C23*E23 -> 195216
A24: 19 | B24: Random Rubble stone masonry for foundation and plinth in Cement Sand mortar above 30CM thick wall in: Cement Mortar 1:6 ( 1-Cement : 6-Sand). | C24: 499 | D24: Cum | E24: 1526 | F24: P Cum | G24: =C24*E24 -> 761474
A25: 20 | B25: Supplying and fixing dressed sand or other approved stone shelves, tands in cement mortar 1:3 with fine dressed edges : | G25: =C25*E25 -> 0
A26: 20.1 | B26: 35mm thick. | C26: 45 | D26: Sqm | E26: 385 | G26: =C26*E26 -> 17325
A27: 20.2 | B27: 50mm thick. | C27: 45 | D27: Sqm | E27: 575 | G27: =C27*E27 -> 25875
A28: 21 | B28: Supplying and fixing in walls machine cut and polished stone shelves, tands and sills in CM 1:3 with machine cut edges : Kota Stone 25 to 30 mm thick. | C28: 185 | D28: Sqm | E28: 467 | G28: =C28*E28 -> 86395
A29: 22 | B29: Marble stone flooring table rubbed, 18 mm thick over 20mm (Av.) thick base of CM 1:4 (1 cement : 4 coarse sand) jointing with white cement mortar 1:2 (1 white cement : 2 marble dust) with pigment to match the shade of the marble slab including grinding, rubbing and polishing complete. | G29: =C29*E29 -> 0
A30: 22.1 | B30: Rajnagar 1st quality with light spots. 1501 Cm2 to 3600 Cm2 Tiles | C30: 3414 | D30: Sqm | E30: 1000 | G30: =C30*E30 -> 3414000
A31: 22.2 | B31: Kesriaji (Rikhabdeo).1501 cm2 to 3600 cm2 tiles | C31: 355 | D31: Sqm | E31: 1221 | G31: =C31*E31 -> 433455
A32: 23 | B32: Add extra for doing mirror polishing. | C32: 3464 | D32: Sqm | E32: 92.6 | G32: =C32*E32 -> 320766.4
A33: 24 | B33: Providing and fixing Granite stone slab mirror polished and machine edge cut in walls, pillars, steps, Shelves, Sills Counters, Floors etc. laid on 12mm (Av.) thick base of cement mortar 1:3 (1 cement : 3 coarse sand) jointing with white cement mortar 1:2 (1 white cement : 2 marble dust) with pigment to match the shade of the granite slab complete including rubbing and polishing of : Green / Black / Other granite 1501 Cm2 to 3600 Cm2 Tiles. | C33: 113 | D33: Sqm | E33: 2477 | G33: =C33*E33 -> 279901
A34: 25 | B34: Providing and fixing Ist quality standard White Ivory Glazed Tiles ISI marked [IS:13753] of size 300mm x 200mm in walls, floors, steps, pillars etc. laid on a bed of neat cement slurry finished with flush pointing in white cement mixed with pigment to match the shade of tile complete (excluding the cost of cement plaster). Category-I : Kajariya, Jhonson, Somani make etc. | C34: 5622 | D34: Sqm | E34: 990 | G34: =C34*E34 -> 5565780
A35: 26 | B35: Providing and fixing Ist quality MAT finished ceremic tile size 300x300mm confirming to IS : 13753 colour such as white, grey, ivory, fume red brown in walls, floors, steps, pillars etc. laid on a bed of neat cement slsurry including nicely finished joints using water proof joint filler power (Untile or Roffe make) and finishing with flush pointing in white cement mixed with pigment to match the shade of tile complete (excluding the cost of cement plaster). Category A: Kajaria, Jhonson,Somani make etc. | C35: 543 | D35: sqm | E35: 865 | G35: =C35*E35 -> 469695
A36: 27 | B36: Extra for providing edge moulding (Full) to 18 mm thick marble stone counters, vantities etc. over item No. 7.1 & 7.2 including machine polishing to edge to give high gloss finish etc. complete as per design approved by Engineer-in-Charge. | G36: =C36*E36 -> 0
A37: 27.1 | B37: Marble work | C37: 390 | D37: Mtr | E37: 122 | G37: =C37*E37 -> 47580
A38: 27.2 | B38: Granite work. | C38: 72 | D38: Mtr | E38: 200 | G38: =C38*E38 -> 14400
A39: 28 | B39: P & F Vitrified Porcelain Polished tiles on floor, skirting and steps etc. in different sizes (thickness to be specified by manufacture) with water absortion less than 0.08% and conforming to IS 15622 of approved make in all colour and shade, laid with 20 mm thick CM 1:4 including grouting the joints with white cement and matching pigment etc complete (Oreva, Nitco and equivalent as approved by Engineer-incharge) Size 600 mm x 600 mm | C39: 2566 | D39: Sqm | E39: 1208 | G39: =C39*E39 -> 3099728
A40: 29 | B40: Other Fitting. Providing and Fixing hydraulic door closure ISI marked. | C40: 59 | D40: Each | E40: 674 | G40: =C40*E40 -> 39766
A41: 30 | B41: Providing and fixing external grade board solid core single leaf flush door shutters ISI 2202-67 marked using Phenol formal, dehydreresin in glue both sides with approved steel fittings complete as per Annexure ‘A’ 35 mm thick shutter,commercial veneer both side | C41: 333 | D41: Sqm | E41: 1580 | G41: =C41*E41 -> 526140
A42: 31 | B42: Add extra for Flush doors For External Teak Wood Lipping on flush doors 35mm x6mm | C42: 333 | D42: R mtr | E42: 60 | G42: =C42*E42 -> 19980
A43: 32 | B43: Providing and fixing pressed steel mitred door frames manufactured from commercial mild steel sheet of 1.25 mm (16 gauge) thickness including hinges jamb, lock jamb, head and if required angle threshold of mild steel angle of section 50x25mm, or base ties of 1.25 mm pressed mild steel welded or rigidly fixed together by mechanical means, adjustable lugs with split end tail to each jamb including steel butt hinges 2.5 mm thick with mortar guards, lock strike-plate and shock absorbers as specified and applying a coat of approved steel primer after pre-treatment of the surface as directed by Engineer-in-charge. Profile 'C' | C43: 442 | D43: Mtr | E43: 318 | G43: =C43*E43 -> 140556
A44: 33 | B44: Supply and fixing in cement mortar welded hand railing made out of M.S. round or square bars, flats etc. for staircase or verandah as per design complete in all respect (wooden or PVC hand railing to be paid extra) with priming coat of red oxide. | C44: 4500 | D44: Kg | E44: 73 | G44: =C44*E44 -> 328500
A45: 34 | B45: Providing & fixing steel glazed doors, windows and ventilators shutters of standred rolled steel section joint mitred and welded with steel 13x3mm lugs 10 Cm. long embedded in cement concrete blocks 15x10x10 Cm. of 1:3:6 (1-Cement:3-coarse sand:6-graded stone aggregate 20 mm nominal size) or with wooden plugs and screws or rawl plugs and screws or with fixing clips or with bolts and nuts as required, including providing and fixing of plain glass panes 4mm thick with copper glazing clips and special metal-sash putty of approved make, or metal beading with screws complete including priming coat of approved steel primer, excluding the cost of metal beading and other fittings except necessary hinges of pivots steel handles and peg stay etc. as required. Patially fixed and partially openable fixed area not exceed 33% | C45: 25 | D45: Sqm | E45: 1950 | G45: =C45*E45 -> 48750
A46: 35 | B46: Supplying and fixing fixed wire gauge of 14 mesh x 24 gauge to the metal frame of rolled section by metal beading 20x3mm with suitable screw at not exceeding 150 mm distance. | C46: 25 | D46: Sqm | E46: 472 | G46: =C46*E46 -> 11800
A47: 36 | B47: Providing and fixing Square bars or other flat welded to window, ventilators etc. | C47: 504 | D47: Kg | E47: 64 | G47: =C47*E47 -> 32256
A48: 37 | B48: Providing batta (gola) 75mm x 75mm in cement concrete (1:2:4) including finished with cement mortar 1:3 as per standard design. | C48: 760 | D48: Mtr | E48: 31 | G48: =C48*E48 -> 23560
... A51: 40 | B51: Providing and Fixing at all height all false ceiling of 12.5 mm thick tapered edge Gypsum board conforming to IS : 2095 including providing and fixing of frame work made of special section power pressed from M.S. sheet and galvanized in accordance with zine coating 600 as per IS : 277 and consisting of angle cleats of thick 25 mm wide x 16 mm thick with flanges of 22 mm and 37 mm at 1200 mm center to center one flange fixed to the ceiling with dash fastner 12.5 mm dia x 40 mm long with 6 mm dia bolts to the hangers of 25x25x5mm of required length, and other end of angle hanger being fixed with nut and bolts to G.I. channels 45 mm x 15 mm x 0.9 mm running at the rate of 1200 mm center to center to which the ceiling section 0.5 mm thick bottom wedge of 80 mm with tapered flanges of 26 mm each having clips of 10.5 mm at 450 mm center to center shall be fixed in a direction perpendicular to G.I. channel with connecting clips made out of 2.64mm dia x 230mm long G.I. wire at every junction including fixing the gypsum board with ceiling section and perimeter channels 0.5mm thick 27 mm high having flanges of 20 mm and 30 mm long, the perimeter of ceiling fixed to wall / partition with the help of rawl plugs at 450 mm center to center with 25 mm long drive-all screws @ 230mm interval including jointing and fixing to a flush finish of tapered and square edges of gypsum board with recommended filler paper tapes, finisher and two coats of primer suitable for gypsum board as per manufactures specifications and also including the cost of making openings for right fittings, grills, diffusers, cutouts made with frame of perimeter channels suitably fixed all complete as per drawing and specifications and direction of the Engineer-in-charge but the excluding the cost of painting. | C51: 1201 | D51: Sqm | E51: 985 | G51: =C51*E51 -> 1182985
A52: 41 | B52: Filling of sunk portion of roof with earthen pots of required height including filling voids with 1:2:4 light concrete, using brick bats complete leveling and dressing the surface by 50mm thick cement concrete 1:2:4 as per specification. | C52: 108 | D52: Cum | E52: 900 | F52: P Cum | G52: =C52*E52 -> 97200
A53: 42 | B53: Providing and laying Chequerred plain cement concrete embossed specially manufactured non-slipping tiles of approved make 20 mm thick laid on 20 mm thick bed of cement mortar 1:6 jointed with neat cement slurry complete. | C53: 246 | D53: Sqm | E53: 275 | G53: =C53*E53 -> 67650
A54: 43 | B54: Polished Blue Kota Stone flooring skirting, laid over 20 mm thick base of C.M. 1:4 and jointed with grey cement slurry to match the shade of the slab including rubbing and polishing complete : For area of each slab up to 2001 to 5000 Sq. Cm : (A) 25 mm thick slab. | C54: 2613 | D54: Sqm | E54: 548 | G54: =C54*E54 -> 1431924
A55: 44 | B55: Polished Blue Kota Stone slab in steps, walls, pillars having fine machine cut edges laid on 12mm (Av.) thick cement mortar 1:3 and jointed with grey cement slurry mixed with pigment to match the shade of the slab, including rubbing and polishing complete : 25 mm thick slab area upto 901 to 2000 Sq.Cm. | C55: 70 | D55: Sqm | E55: 578 | G55: =C55*E55 -> 40460
A56: 45 | B56: Random rubble dry stone Kharanja under floor. | C56: 583 | D56: Cum | E56: 455 | F56: P Cum | G56: =C56*E56 -> 265265
A57: 46 | B57: Applying plaster of Paris or lime putty sandala (Bhilwara Practice) over cement plaster surface for making even surface. | C57: 6940 | D57: Sqm | E57: 108 | G57: =C57*E57 -> 749520
A58: 47 | B58: Plaster on new surface on walls in cement sand mortar 1:6 including racking of joint etc. complete fine finished: 20 mm thick. | C58: 23068 | D58: Sqm | E58: 84 | G58: =C58*E58 -> 1937712
A59: 48 | B59: Add extra over item No. 12.1 to 12.12 for plaster work on exterior wall of height more than 4.5M. from plinth level of every additional height of 4.5 Mtr. or part thereof. | C59: 3423 | D59: Sqm | E59: 8.4 | G59: =C59*E59 -> 28753.2
A60: 49 | B60: Making grooves as per design in plaster 10mm to 20mm wide. | C60: 2200 | D60: rmt | E60: 5 | G60: =C60*E60 -> 11000
A61: 50 | B61: Providing and applying white cement based putty over plastered surface to prepare the surface even and smooth complete | C61: 17863 | D61: Sqm | E61: 72 | G61: =C61*E61 -> 1286136
A62: 51 | B62: Distempering with 1st quality acrylic washable distemper (ready mixed) of approved manufacturer and of required shade and colour completeincluding all scaffolding as per manufacturer's specification. Two or more coats on new work including prepartion of base with primer, putty, lippy etc complete in all respect. | C62: 17863 | D62: Sqm | E62: 31 | G62: =C62*E62 -> 553753
A63: 52 | B63: Painting exterior surface of Wall with 100% acrylic exterior paint of approved brand and manufacture to give an even shade with two or more coats including prepartion of base with sand papering, primer, putty, etc complete in all respect. New Work | C63: 6523 | D63: Sqm | E63: 86 | G63: =C63*E63 -> 560978
A64: 53 | B64: Applying priming coat: With ready mix pink or gray primer of approved brand and manufacture on wood work hard and soft wood. | C64: 760 | D64: Sqm | E64: 23 | G64: =C64*E64 -> 17480
A65: 54 | B65: Painting with enamel paint of approved brand and manufacture to give an even shade: Two or more coats on new work. | C65: 1842 | D65: Sqm | E65: 49 | G65: =C65*E65 -> 90258
A66: 55 | B66: Providing & fixing precast cement concrete coping 1:2:4 mix 50 mm thick complete as per specification : --50mm-- | C66: 814 | D66: Sqm | E66: 162 | G66: =C66*E66 -> 131868
A67: 56 | B67: Grading roof water proofing treatment with : Cement concrete 1:2:4 (1-Cement:2-coarse sand :4-graded stone aggregate 20mm nominal size).with water proofing compound as per manufacturers specification | C67: 338 | D67: Cum | E67: 3365 | F67: P Cum | G67: =C67*E67 -> 1137370
A68: 57 | B68: Providing and fixing expansion joint board for building RCC column beams, walls, slab of Polyethylene foam of density 30 to 35 Kg/m3 of Armour Board. 40 mm Thick | C68: 298 | D68: Sqm | E68: 755 | G68: =C68*E68 -> 224990
A69: 58 | B69: Providing and fixing 150 mm wide sheet covering over expansion joints with iron screws as per design to match the colour / shade of wall treatment. Aluminum fluted strips 2 mm thick | C69: 85 | D69: Mtr | E69: 230 | G69: =C69*E69 -> 19550
A70: 59 | B70: Providing and fixing in CM 1:4 double paitam (rebated) stone door window and ventilator frames of approved quarry : Size 125 x 75mm. | C70: 464 | D70: Mtr | E70: 123 | G70: =C70*E70 -> 57072
A71: 60 | B71: Providing and laying water proofing treatment to vertical and horizontal surface of depressed portions of W.C. kitchen and the like consisting of. 1st course of applying cement slurry @ 4.4 Kg./sqm' mixed with water proofing compound 'Impermo' of Snowcem or equivalent conforming to IS : 2645 in recommended proportions. IInd course of 20mm cement plaster 1:3 (1-Cement:3-coarse sand) mixed with water proofing compound in recommended proportion. IIIrd course of applying blown or residual bitumen applied hot a 1.7 Kg. Sqm. of area. Ivth course of 400 micron thick PVC sheet (Overlaps at joints of PVC sheet should be 100mm wide and pasted to each other with bitumen @ Kg/Sam.). | C71: 391 | D71: Sqm | E71: 271 | G71: =C71*E71 -> 105961
A72: 61 | B72: P&F APP (Atactic Polypropylene Polymer) modified free fabricated five layer 2mm thick water proofing membrance, black finished reinforced with glass fibre matt manufactured by Bitumat Company Ltd. Soprema or Tamkoj, consisting of a coat of bitumen primer for bitumen mebrance @ 0.40 Qtl/ sqm by the sub-membrance manufactured of density of 25 degree C, 0.87-0.89Kg/ ltr and viscosity 70-160 CPS over the primer coat the layer of membrance shall be laid using butancetorch also sealing all joints etc. and preparing the surface complete. The vital physically and chemical parameters of the mebrance shall be as under- Joint strength in longitudinal and transverse direction at 23 degree C as 350/300 N/5cm. Tear strength in longitudinal and transverse direction as 60/80N. Softening point of membrane not less than 150 Degree C. Cold flexibility shall be upto 2 C when tested in accordance with ASTM, D-5147 (The laying of mebrane shall be got done through the authorized applicator of the manufacture of membrane). 2mm (for corrugated roof sheets) | C72: 4380 | D72: Sqm | E72: 310 | G72: =C72*E72 -> 1357800
A73: 62 | B73: Extra for covering top membrane with Geotextile, 120gsm non woven, 100 % polyester of thickness 1 to 1.25mm bonded to the membrane with intermittent touch by heating the membrane by Butane Torch as per manufactures recommendation [for Item No. 15.53 to 15.55]. | C73: 4380 | D73: Sqm | E73: 44 | G73: =C73*E73 -> 192720
A74: 63 | B74: Providing & fixing anodizing alumium work (Anodizing to be got done from approved Anodizer) for doors, windows, ventilators and partition with extruded built up standard tubular and other sections of approved make confirming to IS : 733 and IS : 1285 anodised transparent 81 dyed to required shade according to IS : 1868 (Minimum anodic coating of grade AC 15), fixed with rawl plugs and screws or with fixing clips or with expansion hold fasteners including necessary filling up of gas at junctions, at top, bottom and sides with required PVC/neoprene felt etc. Aluminium section shall be smooth, rust free, straight, mitred and jointed mechanically wherever required inlcuding cleat angle Aluminum snap beading for glazing/paneling, C.P. Brass/ Stainless Steel screws, Al. Tower bolt & Al. handle & Al. Aldrop etc. all complete as per architectural drawings and the directions of Engineer-in-charge. (Glazing and peneling to be paid for separately). | G74: =C74*E74 -> 0
A75: 63.1 | B75: For Fixed portion | C75: 606 | D75: Kg | E75: 361 | G75: =C75*E75 -> 218766
A76: 63.2 | B76: For shutters of doors, windows & ventilators incl. providing and fixing hinges/ rollers etc. and making provision for fixing of fittings wherever reqd. (lockes shall be paid for separately). | C76: 4543 | D76: Kg | E76: 415 | G76: =C76*E76 -> 1885345
A77: 64 | B77: Providing and Fixing 12mm thick prelaminated three layer medium density (exterior grade) particle bonded formaldehyde synthetic resin of approved brand and manufacture in paneling fixed in aluminium doors, windows/ stainless steel screws etc. complete as per architectural drawings and direction of engineer-in-charge. Pre-laminated particle board with decorative lamination on both side. | C77: 112 | D77: Sqm | E77: 984 | G77: =C77*E77 -> 110208
A78: 65 | B78: Providing and fixing glazing in aluminium door, window, vintilator shutters and partitions etc. with PVS/ neoprene gasket etc. complete as per the architectural drawings and the directions of engineer-in-charge (Cost. of aluminium snap beading shall be paid in basic item.) with glass panes of 5.0mm thickness (weight not less than 13.75 Kg/Sqm) as per IS : 2835 | C78: 748 | D78: Sqm | E78: 672 | G78: =C78*E78 -> 502656
A79: 66 | B79: P&F double action hydraulic floor spring of approved brand and manufacture to aluminium door shutter confirming to IS : 6315 incl. costof cutting floors as reqd. embedding in floor and cover plate etc. complte as per direction of Engineer in charge. Approved brand like Hardwin Euro superior quality or equivalent for extra heavy doors. | C79: 54 | D79: Each | E79: 2032 | G79: =C79*E79 -> 109728
A80: 67 | B80: P&F expanded grill made of anodised aluminium as per desing and drawing having members section of size 7.5mm x 6.0mm and opening of size 102mm x 99mm to aluminium window/ vent with reqd. screws, Y and H aluminium sec (as per drawing) at the ends and middle joints respectively complete in all respect as per direction of engineer in charge. | C80: 496 | D80: Sqm | E80: 1740 | G80: =C80*E80 -> 863040
A81: 68 | B81: Providing and fixing brass lock without handle for aluminium door, or approved quality, make & design as directed by Engineer inc harge | C81: 54 | D81: Each | E81: 343 | G81: =C81*E81 -> 18522
A82: 69 | B82: Polyester powder coating and electro colouring in various colour and shade approved by Engineer incharge (for item No.16.1.1) Section 63.00 x 38.00mm | C82: 606 | D82: Rmt | E82: 48 | G82: =C82*E82 -> 29088
A83: 70 | B83: Polyster powder coating and electro colouring in various and shade approved by Engineer-in-charge | C83: 748 | D83: Sqm | E83: 310 | G83: =C83*E83 -> 231880
A84: 71 | B84: S & F fixed wire gauge of stainless steel of 14 mesh x 24 gauge to the aluminimum window by Aluminium beading 20x3mm with suitable screws at not exceeding 150 mm distance at all heights with all lead and left with scafolding | C84: 748 | D84: Sqm | E84: 592 | G84: =C84*E84 -> 442816
A85: 72 | B85: Providing and fixing expansion joint board for building RCC column beams, walls, slab of Polyethylene foam of density 30 to 35 Kg/m3 of Armour Board. 20 mm thick | C85: 9 | D85: Sqm | E85: 448 | G85: =C85*E85 -> 4032
A86: 73 | B86: Providing and fixing in position copper plate as per design for expansion joints. | C86: 120 | D86: Kg | E86: 508 | G86: =C86*E86 -> 60960
... A104: 91 | B104: P & F G.I. Pipes (Internal work) with G.I. fittings (IS:1239 Mark) & M.S. clamps including cutting and making good the walls and floors : 'B' Class 25 mm dia nominal bore. | C104: 300 | D104: Rmt | E104: 268 | G104: =C104*E104 -> 80400
A105: 92 | B105: P&F G.I. Pipes (External work) with G.I. fittings (IS:1239 Mark) including trenching &refilling earth etc.' B ' Class | G105: =C105*E105 -> 0
A106: 92.1 | B106: 15mm dia nominal bore | C106: 100 | D106: Rmt | E106: 161 | G106: =C106*E106 -> 16100
A107: 92.2 | B107: 25mm dia nominal bore | C107: 500 | D107: Rmt | E107: 251 | G107: =C107*E107 -> 125500
A108: 92.3 | B108: 32mm dia nominal bore | C108: 800 | D108: Rmt | E108: 323 | G108: =C108*E108 -> 258400
A109: 92.4 | B109: 40mm dia nominal bore | C109: 1000 | D109: Rmt | E109: 452 | G109: =C109*E109 -> 452000
A110: 93 | B110: Making connection of G.I. distribution branch with G.I. main including all fitting. Upto 25mm dia | C110: 4 | D110: Each | E110: 178 | G110: =C110*E110 -> 712
A111: 94 | B111: P&F Bib Cock (IS:8931 Mark), Superior quality of approved make : C.P. Brass bib cock, 15mm nominal bore. | C111: 52 | D111: Each | E111: 564 | G111: =C111*E111 -> 29328
A112: 95 | B112: C.P. Brass swan neck, 15mm nominal bore long body, 15mm nominal bore weight not less than 690 gm. | C112: 34 | D112: Each | E112: 779 | G112: =C112*E112 -> 26486
A113: 96 | B113: P&F Sink Cocks of superior quality & approved made : C.P. Casted spout 15mm. | C113: 63 | D113: Each | E113: 859 | G113: =C113*E113 -> 54117
A114: 97 | B114: P&F Ball Cock (IS: 1703 Mark) with Rod & PVC Ball complete. Brass wt. 1000 gm, 25mm | C114: 20 | D114: Each | E114: 377 | G114: =C114*E114 -> 7540
A115: 98 | B115: P&F Inlet Connection (Angle Valves) Superior quality, of approved make ,for Wash basin, Geyser etc. C.P. Inlet connection 15mm Brass (IS: 8931 Marked). | C115: 122 | D115: Each | E115: 493 | G115: =C115*E115 -> 60146
A116: 99 | B116: P&F 15mm. Dia Connection Pipe of approved quality/make : PVC pipe with C.P. Brass nuts upto length 450mm. | C116: 79 | D116: Each | E116: 85 | G116: =C116*E116 -> 6715
A117: 100 | B117: P&F Full-way valve (IS:778 Mark) or wheel valve of approved make : | G117: =C117*E117 -> 0
A118: 100.1 | B118: Gun-metal 25mm nominal bore | C118: 20 | D118: Each | E118: 541 | G118: =C118*E118 -> 10820
A119: 100.2 | B119: Gun-metal 50mm nominal bore | C119: 10 | D119: Each | E119: 1333 | G119: =C119*E119 -> 13330
...

Sheet GF1_MES
A1: ='gen-abstract'!A2 -> NAME OF WORK :- CONSTRUCTION OF COMMERCIAL COMPLEX FOR PANCHAYAT SAMITI GIRWA, UDAIPUR
A3: PART 'A' CIVIL WORK FIRST FLOOR
A4: DETAILS OF MEASUREMENTS
A5: S.N. | B5: Particulars | C5: Nos. | E5: Length | G5: Breadth | I5: Height | K5: Qty. | L5: Units
B6: Center to center distances
B7: Ground Floor
B8: Main walls 230 mm th. in x and Y Direction
B9: Back Side | C9: 1 | D9: x | E9: 3.58 | J9: = | K9: =IF(C9,C9*E9,"") -> 3.58 | L9: RM
C10: 1 | D10: x | E10: 6.4 | J10: = | K10: =IF(C10,C10*E10,"") -> 6.4 | L10: RM
C11: 1 | D11: x | E11: 3.2 | J11: = | K11: =IF(C11,C11*E11,"") -> 3.2 | L11: RM
C12: 1 | D12: x | E12: 3.2 | J12: = | K12: =IF(C12,C12*E12,"") -> 3.2 | L12: RM
C13: 1 | D13: x | E13: 5.33 | J13: = | K13: =IF(C13,C13*E13,"") -> 5.33 | L13: RM
B14: Left Side | C14: 1 | D14: x | E14: 7.62 | J14: = | K14: =IF(C14,C14*E14,"") -> 7.62 | L14: RM
C15: 1 | D15: x | E15: 4.27 | J15: = | K15: =IF(C15,C15*E15,"") -> 4.27 | L15: RM
C16: 1 | D16: x | E16: 7.62 | J16: = | K16: =IF(C16,C16*E16,"") -> 7.62 | L16: RM
B17: Front Side | C17: 1 | D17: x | E17: 3.58 | J17: = | K17: =IF(C17,C17*E17,"") -> 3.58 | L17: RM
C18: 1 | D18: x | E18: 3.2 | J18: = | K18: =IF(C18,C18*E18,"") -> 3.2 | L18: RM
B19: Right Side | C19: 1 | D19: x | E19: 25.6 | J19: = | K19: =IF(C19,C19*E19,"") -> 25.6 | L19: RM
B20: Staircase | C20: 2 | D20: x | E20: 3.35 | J20: = | K20: =IF(C20,C20*E20,"") -> 6.7 | L20: RM
B21: Lobby/ Shop | C21: 1 | D21: x | E21: 5.49 | J21: = | K21: =IF(C21,C21*E21,"") -> 5.49 | L21: RM
I22: TOTAL | J22: = | K22: =SUM(K9:K21) -> 85.79 | L22: RM
B24: PARAPET WALL 230 MM
B25: Back Side | C25: 1 | D25: x | E25: 3.58 | J25: = | K25: =IF(C25,C25*E25,"") -> 3.58 | L25: RM
C26: 1 | D26: x | E26: 6.4 | J26: = | K26: =IF(C26,C26*E26,"") -> 6.4 | L26: RM
C27: 1 | D27: x | E27: 3.2 | J27: = | K27: =IF(C27,C27*E27,"") -> 3.2 | L27: RM
C28: 1 | D28: x | E28: 3.2 | J28: = | K28: =IF(C28,C28*E28,"") -> 3.2 | L28: RM
C29: 1 | D29: x | E29: 5.33 | J29: = | K29: =IF(C29,C29*E29,"") -> 5.33 | L29: RM
B30: Left Side | C30: 1 | D30: x | E30: 7.62 | J30: = | K30: =IF(C30,C30*E30,"") -> 7.62 | L30: RM
C31: 1 | D31: x | E31: 4.27 | J31: = | K31: =IF(C31,C31*E31,"") -> 4.27 | L31: RM
C32: 1 | D32: x | E32: 7.62 | J32: = | K32: =IF(C32,C32*E32,"") -> 7.62 | L32: RM
B33: Front Side | C33: 1 | D33: x | E33: 3.58 | J33: = | K33: =IF(C33,C33*E33,"") -> 3.58 | L33: RM
C34: 1 | D34: x | E34: 3.2 | J34: = | K34: =IF(C34,C34*E34,"") -> 3.2 | L34: RM
B35: Right Side | C35: 1 | D35: x | E35: 25.6 | J35: = | K35: =IF(C35,C35*E35,"") -> 25.6 | L35: RM
I36: TOTAL | J36: = | K36: =SUM(K25:K35) -> 73.6 | L36: RM
B37: Brick Partition walls in X and Y Direction
B38: Shops 2,3 | C38: 3 | D38: x | E38: 7.39 | J38: = | K38: =IF(C38,C38*E38,"") -> 22.17 | L38: RM
B39: Shops 6,7 in Y Direction | C39: 2 | D39: x | E39: 5.49 | J39: = | K39: =IF(C39,C39*E39,"") -> 10.98 | L39: RM
B40: Shops 6,1 in X Direction | C40: 2 | D40: x | E40: 3.35 | J40: = | K40: =IF(C40,C40*E40,"") -> 6.7 | L40: RM
B41: Shop 7 in X Direction | C41: 1 | D41: x | E41: 3.05 | J41: = | K41: =IF(C41,C41*E41,"") -> 3.05 | L41: RM
B42: Shop 4 in X Direction | C42: 1 | D42: x | E42: 5.26 | J42: = | K42: =IF(C42,C42*E42,"") -> 5.26 | L42: RM
B43: Shop 5 in X Direction | C43: 1 | D43: x | E43: 3.66 | J43: = | K43: =IF(C43,C43*E43,"") -> 3.66 | L43: RM
B44: Shop 8 in Y Direction | C44: 1 | D44: x | E44: 5.49 | J44: = | K44: =IF(C44,C44*E44,"") -> 5.49 | L44: RM
B45: Toilets in Y Direction | C45: 2 | D45: x | E45: 2.13 | J45: = | K45: =IF(C45,C45*E45,"") -> 4.26 | L45: RM
I46: TOTAL | J46: = | K46: =SUM(K38:K45) -> 61.57 | L46: RM
A48: 1 | B48: Earth work in excavation in foundation trenches or drains including dressing of sides and ramming of bottoms, lift up to 1.5 Mtr. including taking out the excavated soil and depositing and refilling of jhiri with watering & ramming and disposal of surplus excavated soil as directed within a lead of 50 meter. All kinds of soil.
B49: Average Width (49.83+18.44)/2=34.14 | C49: 1 | D49: x | E49: 34.14 | F49: x | G49: 37.8 | H49: x | I49: 1.2 | J49: = | K49: =IF(C49,C49*E49*G49*I49,"") -> 1548.5904 | L49: Cum
G51: Total | K51: =SUM(K49:K50) -> 1548.5904 | L51: Cum
A52: 2 | B52: Filling available excavated earth (excluding rock) in trenches, plinth side of foundation etc. in layers not exceeding 20 cm. in depth , consolidating each deposited layer by ramming and watering including lead upto 50Mtr. and lift upto 1.5Mtr. | I52: =E53*G53 -> 0
B53: Average Width (49.83+18.44)/2=34.14
B54: Area of Open Excavation | C54: 1 | D54: x | E54: 34.14 | F54: x | G54: 37.8 | J54: = | K54: =IF(C54,C54*E54*G54,"") -> 1290.492 | L54: Sqm
B55: Deductions
B56: Footing Area
B57: C1 | C57: 1 | D57: x | E57: 2 | F57: x | G57: 2.3 | J57: = | K57: =IF(C57,C57*E57*G57,"") -> 4.6 | L57: Sqm
B58: C2 | C58: 1 | D58: x | E58: 2.4 | F58: x | G58: 2.7 | J58: = | K58: =IF(C58,C58*E58*G58,"") -> 6.48 | L58: Sqm
B59: C3 | C59: 1 | D59: x | E59: 2.9 | F59: x | G59: 3.1 | J59: = | K59: =IF(C59,C59*E59*G59,"") -> 8.99 | L59: Sqm
B60: C4 | C60: 1 | D60: x | E60: 2.1 | F60: x | G60: 2.3 | J60: = | K60: =IF(C60,C60*E60*G60,"") -> 4.83 | L60: Sqm
B61: C5 | C61: 1 | D61: x | E61: 2.9 | F61: x | G61: 3.1 | J61: = | K61: =IF(C61,C61*E61*G61,"") -> 8.99 | L61: Sqm
B62: C6 | C62: 1 | D62: x | E62: 2.7 | F62: x | G62: 2.9 | J62: = | K62: =IF(C62,C62*E62*G62,"") -> 7.83 | L62: Sqm
B63: C7 | C63: 1 | D63: x | E63: 2.7 | F63: x | G63: 2.9 | J63: = | K63: =IF(C63,C63*E63*G63,"") -> 7.83 | L63: Sqm
B64: C8 | C64: 1 | D64: x | E64: 2.1 | F64: x | G64: 2.3 | J64: = | K64: =IF(C64,C64*E64*G64,"") -> 4.83 | L64: Sqm
B65: C9 | C65: 1 | D65: x | E65: 2.9 | F65: x | G65: 3.1 | J65: = | K65: =IF(C65,C65*E65*G65,"") -> 8.99 | L65: Sqm
B66: C10 | C66: 1 | D66: x | E66: 2.9 | F66: x | G66: 3.1 | J66: = | K66: =IF(C66,C66*E66*G66,"") -> 8.99 | L66: Sqm
B67: C11 | C67: 1 | D67: x | E67: 2.4 | F67: x | G67: 2.6 | J67: = | K67: =IF(C67,C67*E67*G67,"") -> 6.24 | L67: Sqm
B68: C12 | C68: 1 | D68: x | E68: 3 | F68: x | G68: 3.2 | J68: = | K68: =IF(C68,C68*E68*G68,"") -> 9.6 | L68: Sqm
... B74: C18 | C74: 1 | D74: x | E74: 2.3 | F74: x | G74: 2.5 | J74: = | K74: =IF(C74,C74*E74*G74,"") -> 5.75 | L74: Sqm
G75: Total Deductions | J75: - | K75: =SUM(K57:K74) -> 121.91 | L75: Sqm
B77: Net earth Filling Area | E77: =K54 -> 1290.492 | F77: - | G77: =K75 -> 121.91 | J77: = | K77: =E77-G77 -> 1168.582 | L77: Sqm
B79: Qty. in Filling | E79: =K77 -> 1168.582 | F79: x | G79: 1 | J79: = | K79: =E79*G79 -> 1168.582 | L79: Cum
G80: Total | K80: =SUM(K79) -> 1168.582 | L80: Cum
A81: 3 | B81: Providing and injection Chloropyrifous Emulsifiable concentrate 20 % with 1 % concentration for PRE-CONSGTRUCTIONAL Anti termite treatment as per IS 6313 part III and amended from time to time and creating a continous chemical barrier under and around the column pits, wall trenches, basement excavation, top surface of plinth filling, junction of wall and floor along the external perimeter of building expansion joints, over the top surface of consolidated earth of which aproch is to be laid surrounding of pipes and conduits etc. complete as per specification (Plinth floor area only shall be measured for payment.)
B82: Average Width (49.83+18.44)/2=34.14
B83: Area of Open Excavation | C83: 1 | D83: x | E83: 34.14 | F83: x | G83: 37.8 | J83: = | K83: =IF(C83,C83*E83*G83,"") -> 1290.492 | L83: Sqm
G84: Total | K84: =SUM(K83) -> 1290.492 | L84: Sqm
A85: 4 | B85: Providing and laying in position cement concrete including curing compaction etc. of specified grade excluding the cost of centering and shuttering =All up to plinth leve 1:4:8 (1Cement :4 Coarse Sand :8 Graded stone aggregate 40 mm nominal size
B86: FOOTING
B87: F1 | C87: 1 | D87: x | E87: 2 | F87: x | G87: 2.3 | H87: x | I87: 0.3 | J87: = | K87: =IF(C87,C87*E87*G87*I87,"") -> 1.38 | L87: Cum
B88: F2 | C88: 1 | D88: x | E88: 2.4 | F88: x | G88: 2.7 | H88: x | I88: 0.3 | J88: = | K88: =IF(C88,C88*E88*G88*I88,"") -> 1.944 | L88: Cum
B89: F3 | C89: 1 | D89: x | E89: 2.9 | F89: x | G89: 3.1 | H89: x | I89: 0.3 | J89: = | K89: =IF(C89,C89*E89*G89*I89,"") -> 2.697 | L89: Cum
B90: F4 | C90: 1 | D90: x | E90: 2.1 | F90: x | G90: 2.3 | H90: x | I90: 0.3 | J90: = | K90: =IF(C90,C90*E90*G90*I90,"") -> 1.449 | L90: Cum
B91: F5 | C91: 1 | D91: x | E91: 2.9 | F91: x | G91: 3.1 | H91: x | I91: 0.3 | J91: = | K91: =IF(C91,C91*E91*G91*I91,"") -> 2.697 | L91: Cum
B92: F6 | C92: 1 | D92: x | E92: 2.7 | F92: x | G92: 2.9 | H92: x | I92: 0.3 | J92: = | K92: =IF(C92,C92*E92*G92*I92,"") -> 2.349 | L92: Cum
B93: F7 | C93: 1 | D93: x | E93: 2.7 | F93: x | G93: 2.9 | H93: x | I93: 0.3 | J93: = | K93: =IF(C93,C93*E93*G93*I93,"") -> 2.349 | L93: Cum
B94: F8 | C94: 1 | D94: x | E94: 2.1 | F94: x | G94: 2.3 | H94: x | I94: 0.3 | J94: = | K94: =IF(C94,C94*E94*G94*I94,"") -> 1.449 | L94: Cum
B95: F9 | C95: 1 | D95: x | E95: 2.9 | F95: x | G95: 3.1 | H95: x | I95: 0.3 | J95: = | K95: =IF(C95,C95*E95*G95*I95,"") -> 2.697 | L95: Cum
B96: F10 | C96: 1 | D96: x | E96: 2.9 | F96: x | G96: 3.1 | H96: x | I96: 0.3 | J96: = | K96: =IF(C96,C96*E96*G96*I96,"") -> 2.697 | L96: Cum
B97: F11 | C97: 1 | D97: x | E97: 2.4 | F97: x | G97: 2.6 | H97: x | I97: 0.3 | J97: = | K97: =IF(C97,C97*E97*G97*I97,"") -> 1.872 | L97: Cum
B98: F12 | C98: 1 | D98: x | E98: 3 | F98: x | G98: 3.2 | H98: x | I98: 0.3 | J98: = | K98: =IF(C98,C98*E98*G98*I98,"") -> 2.88 | L98: Cum
... B104: F18 | C104: 1 | D104: x | E104: 2.3 | F104: x | G104: 2.5 | H104: x | I104: 0.3 | J104: = | K104: =IF(C104,C104*E104*G104*I104,"") -> 1.725 | L104: Cum
B105: Basement Wall and Raft AREA | C105: 1 | D105: x | E105: =K77 -> 1168.582 | F105: x | G105: 1 | H105: x | I105: 0.15 | J105: = | K105: =IF(C105,C105*E105*G105*I105,"") -> 175.2873 | L105: Cum
G107: Total Qty. | K107: =SUM(K87:K106) -> 211.8603 | L107: Cum
A108: 5 | B108: Providing and laying in position specified grade of reinforcement cement concrete all RCC structural elements upto plinth level including curing compaction finishing with rendering in cement sand mortar 1:3 ( 1 cement : 3 coarse sand) and making good the joints excluding the cost of centering shuttering and reinforcementlevel. M25 grade Design mix
B109: FOOTING
B110: F1 | C110: 1 | D110: x | E110: 1.7 | F110: x | G110: 2 | H110: x | I110: 0.6 | J110: = | K110: =IF(C110,C110*E110*G110*I110,"") -> 2.04 | L110: Cum
B111: F2 | C111: 1 | D111: x | E111: 2.1 | F111: x | G111: 2.4 | H111: x | I111: 0.75 | J111: = | K111: =IF(C111,C111*E111*G111*I111,"") -> 3.78 | L111: Cum
B112: F3 | C112: 1 | D112: x | E112: 2.6 | F112: x | G112: 2.8 | H112: x | I112: 0.8 | J112: = | K112: =IF(C112,C112*E112*G112*I112,"") -> 5.824 | L112: Cum
B113: F4 | C113: 1 | D113: x | E113: 1.8 | F113: x | G113: 2 | H113: x | I113: 0.6 | J113: = | K113: =IF(C113,C113*E113*G113*I113,"") -> 2.16 | L113: Cum
B114: F5 | C114: 1 | D114: x | E114: 2.6 | F114: x | G114: 2.8 | H114: x | I114: 0.9 | J114: = | K114: =IF(C114,C114*E114*G114*I114,"") -> 6.552 | L114: Cum
B115: F6 | C115: 1 | D115: x | E115: 2.4 | F115: x | G115: 2.6 | H115: x | I115: 0.75 | J115: = | K115: =IF(C115,C115*E115*G115*I115,"") -> 4.68 | L115: Cum
B116: F7 | C116: 1 | D116: x | E116: 2.4 | F116: x | G116: 2.6 | H116: x | I116: 0.75 | J116: = | K116: =IF(C116,C116*E116*G116*I116,"") -> 4.68 | L116: Cum
B117: F8 | C117: 1 | D117: x | E117: 1.8 | F117: x | G117: 2 | H117: x | I117: 0.6 | J117: = | K117: =IF(C117,C117*E117*G117*I117,"") -> 2.16 | L117: Cum
...

Sheet sanitary-abs
A1: ='gen-abstract'!A2 -> NAME OF WORK :- CONSTRUCTION OF COMMERCIAL COMPLEX FOR PANCHAYAT SAMITI GIRWA, UDAIPUR
A2: PART 'B' SANITARY & WATER SUPPLY WORK
A3: ABSTRACT OF COST
A4: S.No. | B4: Particulars. | C4: Quantity | E4: Rate | F4: Unit | G4: Amount
A5: 1 | B5: P & F Indian Type white glazed vitreous china Ist quality WC Orissa Pan (IS : 2556 Mark) with 100 mm vitreous china P or S trap including cutting and making good the wall and floor. Size 580x440 mm | C5: 3 | D5: Nos. | E5: 890 | F5: Each | G5: =IF(C5,ROUNDUP(C5*E5,0),"") -> 2670
A6: =A5+1 -> 2 | B6: P & F Flush cock/Flush valve (IS : 9758 Mark) for WC of approved quality make : C.P. Brass concealed 25 mm | C6: 3 | D6: Nos. | E6: 650 | F6: Each | G6: =IF(C6,ROUNDUP(C6*E6,0),"") -> 1950
A7: =IF(A6,A6+1,#REF!+1) -> 3 | B7: P & F WVC wash basin (Ist quality, IS : 2556 Mark) of approved make with C.I. brackets duly painted 1 No. 15 mm C.P. Pillar cock (IS : 8934 Mark) & 32 mm C.P. Brass waste coupling of approved make, 25 mm G.I. waste pipe complete including cutting and making good the wall size 580mmx450mm. | C7: =sanitary_MEASUR!K12 -> 3 | D7: Nos. | E7: 1250 | F7: Each | G7: =IF(C7,ROUNDUP(C7*E7,0),"") -> 3750
A8: =IF(A7,A7+1,A6+1) -> 4 | B8: P&F beveled edge mirror of special glass of approved make (Atul or equivalent) complete with 6 mm thick Asbestos Cement sheet ground fixed to wooden screws & washers sizes 600 x 450 mm x 4 mm thick. | C8: =sanitary_MEASUR!K13 -> 3 | D8: Nos. | E8: 210 | F8: Each | G8: =IF(C8,ROUNDUP(C8*E8,0),"") -> 630
A9: =IF(A8,A8+1,A7+1) -> 5 | B9: P & F grating of approved/quality make : Cast iron. | C9: =sanitary_MEASUR!K17 -> 6 | D9: Nos. | E9: 30 | F9: Each | G9: =IF(C9,ROUNDUP(C9*E9,0),"") -> 180
A10: =IF(A9,A9+1,A8+1) -> 6 | B10: P & F GI Pipes (Internal work) with G.I. fittings (IS : 1239 Mark) & MS clamps, including cutting and making good the wall and floors : | G10: =IF(C10,ROUNDUP(C10*E10,0),"")
A11: A. | B11: 15 mm Dai nominal bore `B’ Class. | C11: =sanitary_MEASUR!K22 -> 27 | D11: RM | E11: 70 | F11: P RM | G11: =IF(C11,ROUNDUP(C11*E11,0),"") -> 1890
A12: B. | B12: 25 mm Dai nominal bore `B’ Class | C12: =sanitary_MEASUR!K27 -> 90.6 | D12: RM | E12: 117 | F12: P RM | G12: =IF(C12,ROUNDUP(C12*E12,0),"") -> 10601
A13: 7 | B13: P & F GI Pipes (External work) with G.I. fittings (IS : 1239 Mark) , including trenching and refilling earth etc. : | G13: =IF(C13,ROUNDUP(C13*E13,0),"")
A14: A. | B14: 25 mm Dai nominal bore `B’ Class. | C14: =sanitary_MEASUR!K32 -> 120 | D14: RM | E14: 98 | F14: P RM | G14: =IF(C14,ROUNDUP(C14*E14,0),"") -> 11760
A15: =A13+1 -> 8 | B15: Making connection of G.I. distribution branch with G.I. main including all fittings . (a) upto 25 mm Dai. | C15: =sanitary_MEASUR!K35 -> 9 | D15: Nos. | E15: 100 | F15: Each | G15: =IF(C15,ROUNDUP(C15*E15,0),"") -> 900
A16: 9 | B16: P & F Bib Cock (IS : 8931 Mark) superior quality of approved make : Brass 400 gram 15 mm | C16: =sanitary_MEASUR!K39 -> 4 | D16: Nos. | E16: 120 | F16: Each | G16: =IF(C16,ROUNDUP(C16*E16,0),"") -> 480
A17: =IF(A16,A16+1,#REF!+1) -> 10 | B17: P & F Stop Cock (IS : 8931 Mark) superior quality of approved make : Brass 400 gram 15 mm | C17: =sanitary_MEASUR!K42 -> 3 | D17: Nos. | E17: 120 | F17: Each | G17: =IF(C17,ROUNDUP(C17*E17,0),"") -> 360
A18: 11 | B18: P/F full way valve (IS:778 Mark) or wheel valve of approved make: gun metal | G18: =IF(C18,ROUNDUP(C18*E18,0),"")
B19: (A) 15 mm | C19: =sanitary_MEASUR!K46 -> 3 | D19: Nos. | E19: 150 | F19: Each | G19: =IF(C19,ROUNDUP(C19*E19,0),"") -> 450
B20: (B) 25 mm | C20: =sanitary_MEASUR!K49 -> 2 | D20: Nos. | E20: 300 | F20: Each | G20: =IF(C20,ROUNDUP(C20*E20,0),"") -> 600
A21: =IF(A18,A18+1,#REF!+1) -> 12 | B21: P & F PVC Storage Tank confirming to IS standards of approved make with cover, 25 mm Dai 1 M long C.I. over flow pipe & 25 cm. long wash out pipe with plug and socket, including making connection, etc. complete of approved design: | G21: =IF(C21,ROUNDUP(C21*E21,0),"")
B22: (A) 1000 (liters capacity). | C22: 4 | D22: Nos. | E22: =5000 -> 5000 | F22: Each | G22: =IF(C22,ROUNDUP(C22*E22,0),"") -> 20000
B23: (B) 500 (liters capacity). | C23: =sanitary_MEASUR!K52 -> 1 | D23: Nos. | E23: =2500 -> 2500 | F23: Each | G23: =IF(C23,ROUNDUP(C23*E23,0),"") -> 2500
A24: =IF(A21,A21+1,A18+1) -> 13 | B24: P & F Ball Cock (IS : 1703 Mark) with Rod & PVC Ball complete : | G24: =IF(C24,ROUNDUP(C24*E24,0),"")
B25: (A) Brass wt. 400 gram 15 mm. | C25: 5 | D25: Nos. | E25: 150 | F25: Each | G25: =IF(C25,ROUNDUP(C25*E25,0),"") -> 750
A26: =IF(A24,A24+1,A21+1) -> 14 | B26: Providing and fixing Unplasticized Poly Vinyl Chloride (UPVC) SWR pipes type B for soil and rain and waste discharge system (IS:13592 : 1992 marked) of approved quality/ make including jointing the pipes complete. | G26: =IF(C26,ROUNDUP(C26*E26,0),"")
B27: (A) 110 mm dia. | C27: =sanitary_MEASUR!K60 -> 11 | D27: RM | E27: =200 -> 200 | F27: P RM | G27: =IF(C27,ROUNDUP(C27*E27,0),"") -> 2200
A28: 15 | B28: Providing and fixing Unplasticized Poly Vinyl Chloride (UPVC) SWR pipe fittings type B for soil and rain and waste discharge system (IS:13592 : 1992 marked) of approved quality/ make including jointing the pipes complete. | G28: =IF(C28,ROUNDUP(C28*E28,0),"")
A29: A. | B29: 110 mm dia. Offset | C29: 1 | D29: Nos. | E29: 162 | F29: Each | G29: =IF(C29,ROUNDUP(C29*E29,0),"") -> 162
A30: B. | B30: 110 mm dia. Coupler | C30: 5 | D30: Nos. | E30: 62 | F30: Each | G30: =IF(C30,ROUNDUP(C30*E30,0),"") -> 310
A31: C. | B31: 110 mm dia. Single 'Y' with Door | C31: 1 | D31: Nos. | E31: 199 | F31: Each | G31: =IF(C31,ROUNDUP(C31*E31,0),"") -> 199
A32: D. | B32: 100 mm dia. vent Cowl | C32: =sanitary_MEASUR!K65 -> 3 | D32: Nos. | E32: 34 | F32: Each | G32: =IF(C32,ROUNDUP(C32*E32,0),"") -> 102
A33: E. | B33: 110 mm dia. Single 'Y' | C33: 1 | D33: Nos. | E33: 159 | F33: Each | G33: =IF(C33,ROUNDUP(C33*E33,0),"") -> 159
A34: F. | B34: 110 mm dia. door Bend | C34: 1 | D34: Nos. | E34: 111 | F34: Each | G34: =IF(C34,ROUNDUP(C34*E34,0),"") -> 111
A35: G. | B35: 110 mm dia. Bend 87.5 degree. | C35: 1 | D35: Nos. | E35: 89 | F35: Each | G35: =IF(C35,ROUNDUP(C35*E35,0),"") -> 89
A36: 16 | B36: Providing and fixing Spun Cast Iron (SCI ) Floor Trap (Nahni) of (IS : 3789mark) approved quality /make with socket down or hinged grating including cutting and making good the floor :- size 100x100 mm. | C36: =sanitary_MEASUR!K69 -> 2 | D36: Nos. | E36: 140 | F36: Each | G36: =IF(C36,ROUNDUP(C36*E36,0),"") -> 280
A37: 17 | B37: Construction of manhole in all types of soil inner size 90 x 60 Cm with 300 mm thick masonry in CM 1:6, 10 cm. thick cement concrete 1:5:10 in foundation, 20 mm thick inside plaster in CM 1:6, finished with floating neat cement, 50 mm thick M-15 grade CC flooring, making channels, 80 mm thick stone slab covering with 40 mm thick M-15 grade C.C. flooring, 25 Kg CI cover with frame of 450 mm Dai. earth work etc. Complete as per approved drawing including disposal of surplus earth within a lead of 50 m. | G37: =IF(C37,ROUNDUP(C37*E37,0),"")
B38: (A) Depth upto 0.5 M | C38: =sanitary_MEASUR!K71 -> 2 | D38: Nos. | E38: 1500 | F38: Each | G38: =IF(C38,ROUNDUP(C38*E38,0),"") -> 3000
B39: (B) Depth 0.5 M to 1.0 M | C39: =sanitary_MEASUR!K72 -> 1 | D39: Nos. | E39: 2050 | F39: Each | G39: =IF(C39,ROUNDUP(C39*E39,0),"") -> 2050
A40: =IF(A37,A37+1,#REF!+1) -> 18 | B40: Supplying and fixing C.I. cover with frame, C.I. gratings for chambers & man holes. | C40: =sanitary_MEASUR!K73 -> 75 | D40: Kg. | E40: 12 | F40: P Kg. | G40: =IF(C40,ROUNDUP(C40*E40,0),"") -> 900
A41: 19 | B41: Providing laying and jointing glazed SW pipes Grade `A’ (IS : 651 marked) of approved make with spun yarn & stiff mixture of cement mortar 1:1 excavation and refilling of earth in all types of soil upto 1.2m depth, SW fittings, including testing of joints etc. complete 100 mm dia. | C41: =sanitary_MEASUR!K80 -> 43 | D41: RM | E41: 95 | F41: P RM | G41: =IF(C41,ROUNDUP(C41*E41,0),"") -> 4085
A42: 20 | B42: Providing & laying CC 1 : 5 : 10 (stone aggregate 40 nominal size) all around SW pipe incl. 15cm thick bed concrete as per Rajasthan PWD specifications (width W=dia of pipe in cm + 40 cm ). 100mm Dai SW pipe | C42: =sanitary_MEASUR!K81 -> 43 | D42: Rm. | E42: 115 | F42: Per Rm. | G42: =IF(C42,ROUNDUP(C42*E42,0),"") -> 4945
A43: 21 | B43: P & F square mouth gully trap `A’ grade (IS : marked) of approved make complete with CI grating frame & cover, masonry chamber is CM 1:6, 100 mm thick CC 1:5:10 base concrete 40 mm thick CC M-15 grade coping, 12 mm thick cement plaster in CM 1:3 complete as per approved design and type: Internal chamber size 300 x 300 mm | C43: =sanitary_MEASUR!K82 -> 3 | D43: No. | E43: 500 | F43: Each | G43: =IF(C43,ROUNDUP(C43*E43,0),"") -> 1500
A44: 22 | B44: P & F 15 mm Dai. Connection pipe of approved quality / make: PVC pipe 450 mm | C44: =sanitary_MEASUR!K84 -> 3 | D44: Nos. | E44: 35 | F44: Each | G44: =IF(C44,ROUNDUP(C44*E44,0),"") -> 105
A45: 23 | B45: P & F 1 st quality WVC Urinal (IS: 2556 mark), with 25mm dia G.I. waste pipe, couplings, concealed iron brackets or screws etc. : Flat Back (small) size 456 x 355 X 265 mm. | C45: 2 | D45: Nos. | E45: 450 | F45: Each | G45: =IF(C45,ROUNDUP(C45*E45,0),"") -> 900
A46: 24 | B46: P & F Marble Urinal Partition slab both sides polished of approved design cut from marble size 900 X 600mm Makrana 'Adanga' or Raj Nagar 1st quality White or Andhi Indo-Italian marble. Trap size 150 x 100 mm, 7.20 Kg C.I. cover with frame . | C46: 2 | D46: No. | E46: 425 | F46: Each | G46: =IF(C46,ROUNDUP(C46*E46,0),"") -> 850
D47: Total | F47: Rs. | G47: =SUM(G5:G46) -> 81418
G49: CHARTERED ENGINEER,
G50: TEJHANS INVESTMENTS, UDAIPUR

Sheet sanitary_MEASUR
A1: ='gen-abstract'!A2 -> NAME OF WORK :- CONSTRUCTION OF COMMERCIAL COMPLEX FOR PANCHAYAT SAMITI GIRWA, UDAIPUR
A2: PART 'B' SANITARY & WATER SUPPLY WORK
A3: DETAILS OF MEASUREMENTS
A4: S.N. | B4: Particulars | C4: Nos. | E4: Length | G4: Breadth | I4: Height | K4: Qty. | L4: Units
A5: 1 | B5: P & F Indian Type white glazed vitreous china Ist quality WC Orissa Pan (IS : 2556 Mark) with 100 mm vitreous china P or S trap including cutting and making good the wall and floor. Size 580x440 mm
C6: 3 | D6: x | E6: 1 | J6: =IF(K6,"=","") -> = | K6: =C6*E6 -> 3 | L6: Nos.
A7: =A5+1 -> 2 | B7: P & F Flush cock/Flush valve (IS : 9758 Mark) for WC of approved quality make : C.P. Brass concealed 25 mm | J7: =IF(K7,"=","")
C8: 3 | D8: x | E8: 1 | J8: =IF(K8,"=","") -> = | K8: =C8*E8 -> 3 | L8: Nos.
H9: Total | J9: =IF(K9,"=","") -> = | K9: =SUM(K8:K8) -> 3 | L9: Nos.
A10: =IF(A7,A7+1,A5+1) -> 3 | J10: =IF(K10,"=","")
C11: 3 | D11: x | E11: 1 | J11: =IF(K11,"=","") -> = | K11: =C11*E11 -> 3 | L11: Nos.
H12: Total | J12: =IF(K12,"=","") -> = | K12: =SUM(K11:K11) -> 3 | L12: Nos.
A13: =IF(A10,A10+1,A7+1) -> 4 | B13: P&F bevelled edge mirror of special glass of approved make (Atul or equivalent) complete with 6 mm thick Asbestos Cement sheet ground fixed to wooden screws & washers sizes 600 x 450 mm x 4 mm thick. | C13: =K12 -> 3 | D13: x | E13: 1 | J13: =IF(K13,"=","") -> = | K13: =C13*E13 -> 3 | L13: Nos.
A15: 5 | B15: P & F grating of approved/quality make : Cast iron. | J15: =IF(K15,"=","")
B16: G.F. | C16: 6 | D16: x | E16: 1 | J16: =IF(K16,"=","") -> = | K16: =C16*E16 -> 6 | L16: Nos.
H17: Total | J17: =IF(K17,"=","") -> = | K17: =SUM(K16:K16) -> 6 | L17: Nos.
A18: 6 | B18: P & F GI Pipes (Internal work) with G.I. fittings (IS : 1239 Mark) & MS clamps, including cutting and making good the walls and floors : | J18: =IF(K18,"=","")
A19: A. | B19: 15 mm dia nominal bore `B’ Class. | J19: =IF(K19,"=","")
B20: W.C. Internal plumbing | C20: 3 | D20: x | E20: 4.5 | J20: =IF(K20,"=","") -> = | K20: =C20*E20 -> 13.5 | L20: RM
B21: W.B. Internal plumbing | C21: 3 | D21: x | E21: 4.5 | J21: =IF(K21,"=","") -> = | K21: =C21*E21 -> 13.5 | L21: RM
H22: Total | J22: =IF(K22,"=","") -> = | K22: =SUM(K19:K21) -> 27 | L22: RM
A23: B. | B23: 25 mm dia nominal bore `B’ Class | J23: =IF(K23,"=","")
B24: Uptake pipes | C24: 2 | D24: x | E24: 16.2 | J24: =IF(K24,"=","") -> = | K24: =C24*E24 -> 32.4 | L24: RM
B25: Down take | C25: 3 | D25: x | E25: 14 | J25: =IF(K25,"=","") -> = | K25: =C25*E25 -> 42 | L25: RM
B26: Down take for W.C. | C26: 2 | D26: x | E26: 8.1 | J26: =IF(K26,"=","") -> = | K26: =C26*E26 -> 16.2 | L26: RM
H27: Total | J27: =IF(K27,"=","") -> = | K27: =SUM(K23:K26) -> 90.6 | L27: RM
A28: =A18+1 -> 7 | B28: P & F GI Pipes (External work) with G.I. fittings (IS : 1239 Mark) , including trenching and refilling earth etc. : | J28: =IF(K28,"=","")
A29: A. | B29: 25 mm dia nominal bore `B’ Class. | J29: =IF(K29,"=","")
B30: Ring main | C30: 2 | D30: x | E30: 30 | J30: =IF(K30,"=","") -> = | K30: =C30*E30 -> 60 | L30: RM
B31: Court yard | C31: 4 | D31: x | E31: 15 | J31: =IF(K31,"=","") -> = | K31: =C31*E31 -> 60 | L31: RM
H32: Total | J32: =IF(K32,"=","") -> = | K32: =SUM(K30:K31) -> 120 | L32: RM
A33: =A28+1 -> 8 | B33: Making connection of G.I. distribution branch with G.I. main including all fittings . (a) upto 25 mm dia. | J33: =IF(K33,"=","")
B34: Toilets | C34: 3 | D34: x | E34: 3 | J34: =IF(K34,"=","") -> = | K34: =C34*E34 -> 9 | L34: Nos.
H35: Total | J35: =IF(K35,"=","") -> = | K35: =SUM(K34:K34) -> 9 | L35: Nos.
A36: =A33+1 -> 9 | B36: P & F Bib Cock (IS : 8931 Mark) superior quality of approved make : Brass 400 gram 15 mm | J36: =IF(K36,"=","")
B37: W.C. | C37: 3 | D37: x | E37: 1 | J37: =IF(K37,"=","") -> = | K37: =C37*E37 -> 3 | L37: Nos.
B38: Court Yard | C38: 1 | D38: x | E38: 1 | J38: =IF(K38,"=","") -> = | K38: =C38*E38 -> 1 | L38: Nos.
H39: Total | J39: =IF(K39,"=","") -> = | K39: =SUM(K37:K38) -> 4 | L39: Nos.
A40: =IF(A36,A36+1,#REF!+1) -> 10 | B40: P & F Stop Cock (IS : 8931 Mark) superior quality of approved make : Brass 400 gram 15 mm | J40: =IF(K40,"=","")
B41: W.B. | C41: 3 | D41: x | E41: 1 | J41: =IF(K41,"=","") -> = | K41: =C41*E41 -> 3 | L41: Nos.
H42: Total | J42: =IF(K42,"=","") -> = | K42: =SUM(K41:K41) -> 3 | L42: Nos.
A43: 11 | B43: P/F full way valve (IS:778 Mark) or wheel valve of approved make: gun metal | J43: =IF(K43,"=","")
B44: (A) 15 mm | J44: =IF(K44,"=","")
B45: G.F. units | C45: 3 | D45: x | E45: 1 | J45: =IF(K45,"=","") -> = | K45: =C45*E45 -> 3 | L45: Nos.
H46: Total | J46: =IF(K46,"=","") -> = | K46: =SUM(K45) -> 3 | L46: Nos.
B47: (B) 25 mm | J47: =IF(K47,"=","")
B48: Tanks | C48: 2 | D48: x | E48: 1 | J48: =IF(K48,"=","") -> = | K48: =C48*E48 -> 2 | L48: Nos.
H49: Total | J49: =IF(K49,"=","") -> = | K49: =SUM(K48:K48) -> 2 | L49: Nos.
A50: =IF(A43,A43+1,#REF!+1) -> 12 | B50: P & F PVC Storage Tank confirming to IS standards of approved make with cover, 25 mm dia 1 M long C.I. over flow pipe & 25 cm. long wash out pipe with plug and socket, including making connection, etc. complete of approved design: | J50: =IF(K50,"=","")
B51: (A) 1000 (litres capacity). | C51: 4 | D51: x | E51: 1 | J51: =IF(K51,"=","") -> = | K51: =C51*E51 -> 4 | L51: Nos.
B52: (B) 500 (litres capacity). | C52: 1 | D52: x | E52: 1 | J52: =IF(K52,"=","") -> = | K52: =C52*E52 -> 1 | L52: Nos.
A53: =IF(A50,A50+1,A43+1) -> 13 | B53: P & F Ball Cock (IS : 1703 Mark) with Rod & PVC Ball complete : | J53: =IF(K53,"=","")
B54: (A) Brass wt. 400 gram 15 mm. | C54: 5 | D54: x | E54: 1 | J54: =IF(K54,"=","") -> = | K54: =C54*E54 -> 5 | L54: Nos.
A55: =IF(A53,A53+1,A50+1) -> 14 | J55: =IF(K55,"=","")
B56: (A) 110 mm dia.
B57: Horizontal Internal | J57: =IF(K57,"=","")
B58: W.C. | C58: 3 | D58: x | E58: 2.2 | J58: =IF(K58,"=","") -> = | K58: =C58*E58 -> 6.6 | L58: RM
B59: W.B. | C59: 2 | D59: x | E59: 2.2 | J59: =IF(K59,"=","") -> = | K59: =C59*E59 -> 4.4 | L59: RM
H60: Total | J60: =IF(K60,"=","") -> = | K60: =SUM(K58:K59) -> 11 | L60: RM
A61: 15 | B61: Providing and fixing Unplasticized Poly Vinyl Chloride (UPVC) SWR pipe fittings type B for soil and rain and waste discharge system (IS:13592 : 1992 marked) of approved quality/ make including jointing the pipes complete. | J61: =IF(K61,"=","")
A62: A. | B62: 110 mm dia. Offset | C62: 1 | D62: x | E62: 1 | J62: =IF(K62,"=","") -> = | K62: =C62*E62 -> 1 | L62: Nos.
A63: B. | B63: 110 mm dia. Coupler | C63: 5 | D63: x | E63: 1 | J63: =IF(K63,"=","") -> = | K63: =C63*E63 -> 5 | L63: Nos.
A64: C. | B64: 110 mm dia. Single 'Y' with Door | C64: 1 | D64: x | E64: 1 | J64: =IF(K64,"=","") -> = | K64: =C64*E64 -> 1 | L64: Nos.
A65: D. | B65: 100 mm dia. vent Cowl | C65: 3 | D65: x | E65: 1 | J65: =IF(K65,"=","") -> = | K65: =C65*E65 -> 3 | L65: Nos.
A66: E. | B66: 110 mm dia. Single 'Y' | C66: 1 | D66: x | E66: 1 | J66: =IF(K66,"=","") -> = | K66: =C66*E66 -> 1 | L66: Nos.
A67: F. | B67: 110 mm dia. door Bend | C67: 1 | D67: x | E67: 1 | J67: =IF(K67,"=","") -> = | K67: =C67*E67 -> 1 | L67: Nos.
A68: G. | B68: 110 mm dia. Bend 87.5 degree. | C68: 1 | D68: x | E68: 1 | J68: =IF(K68,"=","") -> = | K68: =C68*E68 -> 1 | L68: Nos.
A69: =A61+1 -> 16 | B69: Providing and fixing Spun Cast Iron (SCI ) Floor Trap (Nahni) of (IS : 3789mark) approved quality /make with socket down or hinged grating including cutting and making good the floor :- size 100x100 mm. | C69: 2 | D69: x | E69: 1 | J69: =IF(K69,"=","") -> = | K69: =C69*E69 -> 2 | L69: Nos.
A70: 17 | B70: Construction of manhole in all types of soil inner size 90 x 60 Cm with 300 mm thick masonry in CM 1:6, 10 cm. thick cement concrete 1:5:10 in foundation, 20 mm thick inside plaster in CM 1:6, finished with floating neat cement, 50 mm thick M-15 grade CC flooring, making channels, 80 mm thick stone slab covering with 40 mm thick M-15 grade C.C. flooring, 25 Kg CI cover with frame of 450 mm dia. earth work etc. Complete as per approved drawing including disposal of surplus earth within a lead of 50 m | J70: =IF(K70,"=","")
B71: (A) Depth upto 0.5 M | C71: 2 | D71: x'. | E71: 1 | J71: =IF(K71,"=","") -> = | K71: =C71*E71 -> 2 | L71: Nos.
B72: (B) Depth 0.5 M to 1.0 M | C72: 1 | D72: x | E72: 1 | J72: =IF(K72,"=","") -> = | K72: =C72*E72 -> 1 | L72: Nos.
A73: =IF(A70,A70+1,#REF!+1) -> 18 | B73: S & F C.I. cover with frame, C.I. gratings for chambers & man holes. | C73: 3 | D73: x | E73: 25 | J73: =IF(K73,"=","") -> = | K73: =C73*E73 -> 75 | L73: Kg.
J74: =IF(K74,"=","")
A75: =A73+1 -> 19 | B75: Providing laying and jointing glazed SW pipes Grade `A’ (IS : 651 marked) of approved make with spun yarn & stiff mixture of cement mortar 1:1 excavation and refilling of earth in all types of soil upto 1.2m depth, SW fittings, including testing of joints etc. complete 100 mm dia. | J75: =IF(K75,"=","")
B76: Horizontal External | J76: =IF(K76,"=","")
B77: Left Line | C77: 1 | D77: x | E77: 18 | J77: =IF(K77,"=","") -> = | K77: =C77*E77 -> 18 | L77: RM
B78: Back Line | C78: 1 | D78: x | E78: 7 | J78: =IF(K78,"=","") -> = | K78: =C78*E78 -> 7 | L78: RM
B79: To Existing ST | C79: 1 | D79: x | E79: 18 | J79: =IF(K79,"=","") -> = | K79: =C79*E79 -> 18 | L79: RM
H80: Total | J80: =IF(K80,"=","") -> = | K80: =SUM(K77:K79) -> 43 | L80: RM
A81: =A75+1 -> 20 | B81: Providing & laying CC 1 : 5 : 10 (stone aggregate 40 nominal size) all around SW pipe incl. 15cm thick bed concrete as per Rajasthan PWD specifications (width W=dia of pipe in cm + 40 cm ). 100mm dia SW pipe | J81: =IF(K81,"=","") -> = | K81: =K80 -> 43 | L81: RM
A82: =A81+1 -> 21 | B82: P & F square mouth gully trap `A’ grade (IS : marked) of approved make complete with CI grating frame & cover, masonry chamber is CM 1:6, 100 mm thick CC 1:5:10 base concrete 40 mm thick CC M-15 grade coping, 12 mm thick cement plaster in CM 1:3 complete as per approved design and type: Trap size 150 x 100 mm, 7.20 Kg C.I. cover with frame . Internal chamber size 300 x 300 mm | C82: 3 | D82: x | E82: 1 | J82: =IF(K82,"=","") -> = | K82: =C82*E82 -> 3 | L82: Nos.
J83: =IF(K83,"=","")
A84: 22 | B84: P & F 15 mm dia. Connection pipe of approved quality / make: PVC pipe 450 mm | C84: 3 | D84: x | E84: 1 | J84: =IF(K84,"=","") -> = | K84: =C84*E84 -> 3 | L84: Nos.
D88: CHARTERED ENGINEER,
D89: TEJHANS INVESTMENTS, UDAIPUR

Sheet tech report
A1: ='gen-abstract'!A2 -> NAME OF WORK :- CONSTRUCTION OF COMMERCIAL COMPLEX FOR PANCHAYAT SAMITI GIRWA, UDAIPUR
A3: Technical Report
A5: 1. Name of Work | C5: : | D5: Construction of Police Station at AMET
A7: 2. Administrative Sanction | C7: :
A9: 3.Location | C9: : | D9: The proposed Hostels shall be constructed at AMET, Rajsamand
A11: 4. Specifications | C11: : | D11: The general specifications adopted for the work are in accordance with the P.W.D. detailed specifications. Brief specifications are narrated below:-
B13: I Foundation concrete | C13: : | D13: Cement concrete 1:5:10 , 150 mm thick.
B15: II Masonry for Foundation | C15: : | D15: Random rubble stone masonry in cement sand mortar 1:6
B17: III Damp proof coarse | C17: : | D17: 75 mm thick P.C.C. M-15.
B19: IV Super structure masonry | C19: : | D19: Stone masonry in cement sand mortar 1:6 walls.
B21: V Lintels | C21: : | D21: R.C.C. M-15 with M.S. reinforcement.
B23: VI Partition | C23: : | D23: Bricks class 75 in cement sand mortar 1:4 (115 mm thick)
B25: VII Base of Flooring | C25: : | D25: 100 mm thick in 1:5 :10 mix
B27: VIII Flooring | D27: 40 mm thick marble chips flooring.
B29: (c) White Glazed Tiles | C29: : | D29: Hostel Building
D30: In Urinals 1200 mm high Dado, in WC's 900 mm High Dado.
B32: IX Plaster | C32: : | D32: 20 mm thick in cement mortar 1:6 over stone masonry and 20 mm thick in cement mortar 1:6 over brick masonry.
B34: X Joinery frames | C34: : | D34: Door frames of mild steel selection (EZ-7 Section)
B36: XI Door Shutters | C36: : | D36: 35 mm thick fully panelled doors with Assam Teak wood frame with 12 mm thick Shuttering Ply Panels for doors 1005 to 1200 mm wide and for other doors 30 mm thick fully panelled doors with Assam Teak wood frame with 9 mm thick Shuttering Ply Panels.
B38: XII Finishing | C38: : | D38: Colour washing at outside, white washing at inside all rooms and ceilings; enamel paints on wood and steel work.
B40: Sanitary work | C40: : | D40: As per P.W.D. specification.
A42: 5. Scope of work | C42: :
B44: Police Station Building | D44: Plinth Area GF 328 Sqm, FF 10.50 Sqm. Total 339.50 Sqm
D45: Ground Floor with Barrack, Wireless Room, Record Room, SHO Room, IO Room, Malkhana, Office & Male Female lockups, store, staircase 2 toilet blocks. In First floor only head room.
A47: 6. Basis of Estimate | C47: : | D47: Estimate prepared on the basis of PWD B.S.R. -1998.
A49: 7. Estimated Cost | C49: : | D49: Estimated cost of work comes to Rs. 20.00 Lacs. It includes the Prorata charges @ 13%.
A51: 8. Drawings | C51: : | D51: Plan, elevation & section are enclosed.
A54: ASSISTANT ENGINEER, | D54: EXECUTIVE ENGINEER,
A55: P.W.D. Sub Div.- AMET | D55: P.W.D. Div.- AMET

Sheet joinery shedule
A1: Particulars | B1: Size in MM | D1: In 380 mm Wall | E1: In Partition Wall
A2: Steel Shutter | B2: 1200x2100 | C2: D1 | D2: 3
A3: Double Leaf Shutter | B3: 1200x2100 | C3: D2 | D3: 2 | F3: 35
A4: Double Leaf Shutter | B4: 900x2100 | C4: D3 | D4: 2 | F4: 35
A5: Single Leaf Shutter | B5: 1050x2100 | C5: D4 | D5: 3 | F5: 35
A6: Single Leaf Shutter | B6: 900x2100 | C6: D5 | D6: 4 | F6: 35
A7: Single Leaf Shutter | B7: 750x2100 | C7: D6 | D7: 0 | E7: 4 | F7: 30
A9: Windows | B9: 1800x1700 | C9: W1 | D9: 6
A10: Windows | B10: 1200x1700 | C10: W2 | D10: 4
A11: Windows | B11: 900x1700 | C11: W3 | D11: 10
A12: Vents | B12: 1200x600 | C12: V1 | D12: 1
A13: Vents | B13: 900x600 | C13: V2 | D13: 1
A14: Vents | B14: 600x600 | C14: V3 | D14: 5

Sheet Sheet11
A1: 1 | B1: x | C1: 11.75 | D1: =ROUND(C1*0.3048,2) -> 3.58
C2: 21 | G2: 115 | H2: =ROUND(G2*0.3048,2) -> 35.05
C3: 21 | G3: 153.5 | H3: =ROUND(G3*0.3048,2) -> 46.79 | I3: =H2+H3 -> 81.84 | J3: =I3/2 -> 40.92
C4: 17.5 | G4: 159 | H4: =ROUND(G4*0.3048,2) -> 48.46
C5: =SUM(C1:C4) -> 71.25 | D5: =ROUND(C5*0.3048,2) -> 21.72 | G5: 51.5 | H5: =ROUND(G5*0.3048,2) -> 15.7
C6: 21 | D6: =ROUND(C6*0.3048,2) -> 6.4 | E6: =
C7: 69 | D7: =ROUND(C7*0.3048,2) -> 21.03
E8: =SUM(D5:D6) -> 28.12
G14: =1.8^2 -> 3.24
G15: =1.05^2 -> 1.1025
G16: =SUM(G14:G15) -> 4.3425 | H16: =G16^0.5 -> 2.0838666

Sheet Sheet12

Sheet Sheet13

Sheet Sheet14

Sheet Sheet15

Sheet Sheet16
